fmeflowclient/__init__.py
fmeflowclient/__version__.py
fmeflowclient-0.1.6.dist-info/METADATA
fmeflowclient-0.1.6.dist-info/WHEEL
fmeflowclient-0.1.6.dist-info/licenses/LICENSE
fmeflowclient-0.1.6.dist-info/RECORD
