Metadata-Version: 2.4
Name: fmeflowclient
Version: 0.1.6
Summary: A Python client for interacting with FME Flow via its REST API
Project-URL: Homepage, https://github.com/sverker84/fmeflowclient
Project-URL: Issues, https://github.com/sverker84/fmeflowclient/issues
Author-email: Sverker Norlander <sverker.norlander@gmail.com>
License-Expression: MIT
License-File: LICENSE
Keywords: API,Client,FME,FME Flow,REST
Classifier: Development Status :: 3 - Alpha
Classifier: License :: OSI Approved :: MIT License
Classifier: Operating System :: OS Independent
Classifier: Programming Language :: Python :: 3
Requires-Python: >=3.7
Requires-Dist: requests
